Nivel_1/Nivel_2-Seg7_Decoder/Seg7_Decoder.v
module Seg7_Decoder (
    input [3:0] sec_ones, sec_tens, mins,
    output [6:0] sec_ones_seg, sec_tens_seg, mins_seg);

    Decoder Ones (sec_ones, sec_ones_seg);
    Decoder Tens (sec_tens, sec_tens_seg);
    Decoder Mins (mins, mins_seg);

endmodule

module Decoder (input [3:0] entrada, output [6:0] saida);

    assign saida = (entrada == 0) ? 7'b1111110 :
                   (entrada == 1) ? 7'b0110000 :
                   (entrada == 2) ? 7'b1101101 :
                   (entrada == 3) ? 7'b1111001 :
                   (entrada == 4) ? 7'b0110011 :
                   (entrada == 5) ? 7'b1011011 :
                   (entrada == 6) ? 7'b0011111 :
                   (entrada == 7) ? 7'b1110000 :
                   (entrada == 8) ? 7'b1111111 :
                   (entrada == 9) ? 7'b1110011 :
                   7'b0000000;
endmodule

Nivel_1/Nivel_2-Seg7_Decoder/Seg7_Decoder_TB.v
`timescale 1ns/1ps
`include "Seg7_Decoder.v"

module Seg7_Decoder_TB ();
    reg [3:0] sec_ones, sec_tens, mins;
    wire [6:0] saida_ones, saida_tens, saida_mins;

    Seg7_Decoder dut (sec_ones, sec_tens, mins, saida_ones, saida_tens, saida_mins);

    initial
    begin
        $dumpfile("Seg7_Decoder_TB.vcd");
        $dumpvars(0,Seg7_Decoder_TB);

        #0 sec_ones = 4'b0000; sec_tens = 4'b0000; mins = 4'b0000;
        #1 sec_ones = 4'b0001; sec_tens = 4'b0001; mins = 4'b0001;
        #1 sec_ones = 4'b0010; sec_tens = 4'b0010; mins = 4'b0010;
        #1 sec_ones = 4'b0011; sec_tens = 4'b0011; mins = 4'b0011;
        #1 sec_ones = 4'b0100; sec_tens = 4'b0100; mins = 4'b0100;
        #1 sec_ones = 4'b0101; sec_tens = 4'b0101; mins = 4'b0101;
        #1 sec_ones = 4'b0110; sec_tens = 4'b0110; mins = 4'b0110;
        #1 sec_ones = 4'b0111; sec_tens = 4'b0111; mins = 4'b0111;
        #1 sec_ones = 4'b1000; sec_tens = 4'b1000; mins = 4'b1000;
        #1 sec_ones = 4'b1001; sec_tens = 4'b1001; mins = 4'b1001;
        #1 sec_ones = 4'b1010; sec_tens = 4'b1010; mins = 4'b1010;
        #1;

    end
endmodule

Nivel_1/Nivel_2-Seg7_Decoder/Seg7_Decoder_TB.vcd
$date
	Sat Apr 22 15:58:01 2023
$end
$version
	Icarus Verilog
$end
$timescale
	1ps
$end
$scope module Seg7_Decoder_TB $end
$var wire 7 ! saida_tens [6:0] $end
$var wire 7 " saida_ones [6:0] $end
$var wire 7 # saida_mins [6:0] $end
$var reg 4 $ mins [3:0] $end
$var reg 4 % sec_ones [3:0] $end
$var reg 4 & sec_tens [3:0] $end
$scope module dut $end
$var wire 4 ' mins [3:0] $end
$var wire 4 ( sec_ones [3:0] $end
$var wire 4 ) sec_tens [3:0] $end
$var wire 7 * sec_tens_seg [6:0] $end
$var wire 7 + sec_ones_seg [6:0] $end
$var wire 7 , mins_seg [6:0] $end
$scope module Mins $end
$var wire 4 - entrada [3:0] $end
$var wire 7 . saida [6:0] $end
$upscope $end
$scope module Ones $end
$var wire 4 / entrada [3:0] $end
$var wire 7 0 saida [6:0] $end
$upscope $end
$scope module Tens $end
$var wire 4 1 entrada [3:0] $end
$var wire 7 2 saida [6:0] $end
$upscope $end
$upscope $end
$upscope $end
$enddefinitions $end
$comment Show the parameter values. $end
$dumpall
$end
#0
$dumpvars
b1111110 2
b0 1
b1111110 0
b0 /
b1111110 .
b0 -
b1111110 ,
b1111110 +
b1111110 *
b0 )
b0 (
b0 '
b0 &
b0 %
b0 $
b1111110 #
b1111110 "
b1111110 !
$end
#1000
b110000 #
b110000 ,
b110000 .
b110000 !
b110000 *
b110000 2
b110000 "
b110000 +
b110000 0
b1 $
b1 '
b1 -
b1 &
b1 )
b1 1
b1 %
b1 (
b1 /
#2000
b1101101 #
b1101101 ,
b1101101 .
b1101101 !
b1101101 *
b1101101 2
b1101101 "
b1101101 +
b1101101 0
b10 $
b10 '
b10 -
b10 &
b10 )
b10 1
b10 %
b10 (
b10 /
#3000
b1111001 #
b1111001 ,
b1111001 .
b1111001 !
b1111001 *
b1111001 2
b1111001 "
b1111001 +
b1111001 0
b11 $
b11 '
b11 -
b11 &
b11 )
b11 1
b11 %
b11 (
b11 /
#4000
b110011 #
b110011 ,
b110011 .
b110011 !
b110011 *
b110011 2
b110011 "
b110011 +
b110011 0
b100 $
b100 '
b100 -
b100 &
b100 )
b100 1
b100 %
b100 (
b100 /
#5000
b1011011 #
b1011011 ,
b1011011 .
b1011011 !
b1011011 *
b1011011 2
b1011011 "
b1011011 +
b1011011 0
b101 $
b101 '
b101 -
b101 &
b101 )
b101 1
b101 %
b101 (
b101 /
#6000
b11111 #
b11111 ,
b11111 .
b11111 !
b11111 *
b11111 2
b11111 "
b11111 +
b11111 0
b110 $
b110 '
b110 -
b110 &
b110 )
b110 1
b110 %
b110 (
b110 /
#7000
b1110000 #
b1110000 ,
b1110000 .
b1110000 !
b1110000 *
b1110000 2
b1110000 "
b1110000 +
b1110000 0
b111 $
b111 '
b111 -
b111 &
b111 )
b111 1
b111 %
b111 (
b111 /
#8000
b1111111 #
b1111111 ,
b1111111 .
b1111111 !
b1111111 *
b1111111 2
b1111111 "
b1111111 +
b1111111 0
b1000 $
b1000 '
b1000 -
b1000 &
b1000 )
b1000 1
b1000 %
b1000 (
b1000 /
#9000
b1110011 #
b1110011 ,
b1110011 .
b1110011 !
b1110011 *
b1110011 2
b1110011 "
b1110011 +
b1110011 0
b1001 $
b1001 '
b1001 -
b1001 &
b1001 )
b1001 1
b1001 %
b1001 (
b1001 /
#10000
b0 #
b0 ,
b0 .
b0 !
b0 *
b0 2
b0 "
b0 +
b0 0
b1010 $
b1010 '
b1010 -
b1010 &
b1010 )
b1010 1
b1010 %
b1010 (
b1010 /
