Nivel_1/Nivel_2-Timer_InControl/Nivel_3-Timer_InControl/encoder/encoder.v
module encoder (
    input keypad0, keypad1, keypad2, keypad3, keypad4,
    keypad5, keypad6, keypad7, keypad8, keypad9, enablen,
    output reg valid, output reg [3:0] BCD_out 
);
    initial
    begin
        BCD_out <= 4'b1111;
    end

    always @(keypad0 or keypad1 or keypad2 or keypad3 or keypad4 or
    keypad5 or keypad6 or keypad7 or keypad8 or keypad9 or enablen)
    begin
        if (enablen == 0)
        begin
            if (keypad0)
                BCD_out = 4'b0000;
            else if (!keypad0 && keypad1)
                BCD_out = 4'b0001;
            else if (!keypad0 && !keypad1 && keypad2)
                BCD_out = 4'b0010;
            else if (!keypad0 && !keypad1 && !keypad2 && keypad3)
                BCD_out = 4'b0011;
            else if (!keypad0 && !keypad1 && !keypad2 && !keypad3 && keypad4)
                BCD_out = 4'b0100;
            else if (!keypad0 && !keypad1 && !keypad2 && !keypad3 && !keypad4 && keypad5)
                BCD_out = 4'b0101;
            else if (!keypad0 && !keypad1 && !keypad2 && !keypad3 && !keypad4 && !keypad5 && keypad6)
                BCD_out = 4'b0110;
            else if (!keypad0 && !keypad1 && !keypad2 && !keypad3 && !keypad4 && !keypad5 && !keypad6 && keypad7)
                BCD_out = 4'b0111;
            else if (!keypad0 && !keypad1 && !keypad2 && !keypad3 && !keypad4 && !keypad5 && !keypad6 && !keypad7 && keypad8)
                BCD_out = 4'b1000;
            else if (!keypad0 && !keypad1 && !keypad2 && !keypad3 && !keypad4 && !keypad5 && !keypad6 && !keypad7 && !keypad8 && keypad9)
                BCD_out = 4'b1001;
            else
                BCD_out = 4'b1111;
            
            if (keypad0 || keypad1 || keypad2 || keypad3 || keypad4 || keypad5 || keypad6 || keypad7 || keypad8 || keypad9)
                valid = 0;
            else
                valid = 1;
        end
        else
            valid = 1;
    end
endmodule

Nivel_1/Nivel_2-Timer_InControl/Nivel_3-Timer_InControl/encoder/encoder_TB.v
`timescale 1ns/1ps
`include "encoder.v"

module encoder_TB ();
    reg [9:0] keypad;
    reg Nenable;
    wire Valid;
    wire [3:0] BCD;

    encoder dut (keypad[0], keypad[1], keypad[2], keypad[3], keypad[4], keypad[5], keypad[6],
                          keypad[7], keypad[8], keypad[9], Nenable, Valid, BCD);

    initial 
    begin
        $dumpfile("encoder_TB.vcd");
        $dumpvars(0,encoder_TB);

        #0 keypad = 10'b0000000000; Nenable = 1;
        #1 keypad = 10'b0000000000; Nenable = 0;
        #1 keypad = 10'b1000000000; Nenable = 0;
        #1 keypad = 10'b0000000000; Nenable = 0;
        #1 keypad = 10'b0100000000; Nenable = 0;
        #1 keypad = 10'b0010000000; Nenable = 0;
        #1 keypad = 10'b0000100000; Nenable = 0;
        #1 keypad = 10'b0001000000; Nenable = 0;
        #1 keypad = 10'b0000010000; Nenable = 0;
        #1 keypad = 10'b0000000000; Nenable = 0;
        #1 keypad = 10'b0000001000; Nenable = 0;
        #1 keypad = 10'b0000000100; Nenable = 0;
        #1 keypad = 10'b0000000100; Nenable = 1;
        #1 keypad = 10'b0000000000; Nenable = 0;
        #1 keypad = 10'b0000001100; Nenable = 0;
        #1 keypad = 10'b0000000010; Nenable = 0;
        #1 keypad = 10'b0000000001; Nenable = 0;
        #1 keypad = 10'b0000000000; Nenable = 0;
        #1;

    end
endmodule

Nivel_1/Nivel_2-Timer_InControl/Nivel_3-Timer_InControl/encoder/encoder_TB.vcd
$date
	Sun Apr 23 03:20:32 2023
$end
$version
	Icarus Verilog
$end
$timescale
	1ps
$end
$scope module encoder_TB $end
$var wire 1 ! Valid $end
$var wire 4 " BCD [3:0] $end
$var reg 1 # Nenable $end
$var reg 10 $ keypad [9:0] $end
$scope module dut $end
$var wire 1 # enablen $end
$var wire 1 % keypad0 $end
$var wire 1 & keypad1 $end
$var wire 1 ' keypad2 $end
$var wire 1 ( keypad3 $end
$var wire 1 ) keypad4 $end
$var wire 1 * keypad5 $end
$var wire 1 + keypad6 $end
$var wire 1 , keypad7 $end
$var wire 1 - keypad8 $end
$var wire 1 . keypad9 $end
$var reg 4 / BCD_out [3:0] $end
$var reg 1 ! valid $end
$upscope $end
$upscope $end
$enddefinitions $end
$comment Show the parameter values. $end
$dumpall
$end
#0
$dumpvars
b1111 /
0.
0-
0,
0+
0*
0)
0(
0'
0&
0%
b0 $
1#
b1111 "
1!
$end
#1000
0#
#2000
0!
b1001 "
b1001 /
1.
b1000000000 $
#3000
1!
b1111 "
b1111 /
0.
b0 $
#4000
0!
b1000 "
b1000 /
1-
b100000000 $
#5000
b111 "
b111 /
1,
0-
b10000000 $
#6000
b101 "
b101 /
1*
0,
b100000 $
#7000
b110 "
b110 /
0*
1+
b1000000 $
#8000
b100 "
b100 /
1)
0+
b10000 $
#9000
1!
b1111 "
b1111 /
0)
b0 $
#10000
0!
b11 "
b11 /
1(
b1000 $
#11000
b10 "
b10 /
1'
0(
b100 $
#12000
1!
1#
#13000
b1111 "
b1111 /
0'
0#
b0 $
#14000
0!
b10 "
b10 /
1'
1(
b1100 $
#15000
b1 "
b1 /
1&
0'
0(
b10 $
#16000
b0 "
b0 /
1%
0&
b1 $
#17000
1!
b1111 "
b1111 /
0%
b0 $
