Nivel_1/Nivel_2-MS_Timer/Nivel_3-MS_Timer/Counter_MOD10.v
module Counter_MOD10 (
    input wire loadn, clrn, clock, enable,
    input wire [3:0] data,
    output reg [3:0] ones, 
    output reg tc, zero
);

    initial 
    begin
        ones <= 0;    
    end

    always @(posedge clock or negedge clrn) 
    begin
        if (!clrn)
            ones <= 4'b0000;
        else
        begin
            if (!loadn)
                ones <= data;
            else
            begin
                if (enable)
                begin
                    if (ones == 4'b0000)
                        ones <= 4'b1001;
                    else
                        ones <= ones - 1;
                end
            end
        end
    end

    always @(ones or enable)
    begin
        if (ones == 0)
            zero <= 1'b1;
        else
            zero <= 1'b0;
        if (ones == 0 && enable)
                tc <= 1'b1;
            else
                tc <= 1'b0;
    end
    
endmodule

Nivel_1/Nivel_2-MS_Timer/Nivel_3-MS_Timer/TB/Counter_MOD10_TB/Counter_MOD10_TB.v
`timescale 1ns/1ps
`include "..\\..\\Counter_MOD10.v"

module Counter_MOD10_TB ();
    reg load, clear, clk, enab;
    reg [3:0] numero;
    wire [3:0] numero_saida;
    wire tc_saida, zero_saida;

    Counter_MOD10 dut (load, clear, clk, enab, numero, numero_saida, tc_saida, zero_saida);

    initial 
    begin
        $dumpfile("Counter_MOD10_TB.vcd");
        $dumpvars(0,Counter_MOD10_TB);

        // Conta
        #0 load <= 1; clear <= 1; clk <= 0; enab <= 0; numero <= 4'b0000;
        #1 load <= 1; clear <= 1; clk <= 0; enab <= 1; numero <= 4'b0000;
        #1 load <= 1; clear <= 1; clk <= 1; enab <= 1; numero <= 4'b0000;
        #1 load <= 1; clear <= 1; clk <= 0; enab <= 1; numero <= 4'b0000;
        #1 load <= 1; clear <= 1; clk <= 1; enab <= 1; numero <= 4'b0000;
        #1 load <= 1; clear <= 1; clk <= 0; enab <= 1; numero <= 4'b0000;
        #1 load <= 1; clear <= 1; clk <= 1; enab <= 1; numero <= 4'b0000;
        #1 load <= 1; clear <= 1; clk <= 0; enab <= 1; numero <= 4'b0000;
        #1 load <= 1; clear <= 1; clk <= 1; enab <= 1; numero <= 4'b0000;
        #1 load <= 1; clear <= 1; clk <= 0; enab <= 1; numero <= 4'b0000;
        #1 load <= 1; clear <= 1; clk <= 1; enab <= 1; numero <= 4'b0000;
        #1 load <= 1; clear <= 1; clk <= 0; enab <= 1; numero <= 4'b0000;
        #1 load <= 1; clear <= 1; clk <= 1; enab <= 1; numero <= 4'b0000;
        #1 load <= 1; clear <= 1; clk <= 0; enab <= 1; numero <= 4'b0000;
        #1 load <= 1; clear <= 1; clk <= 1; enab <= 1; numero <= 4'b0000;
        #1 load <= 1; clear <= 1; clk <= 0; enab <= 1; numero <= 4'b0000;
        #1 load <= 1; clear <= 1; clk <= 1; enab <= 1; numero <= 4'b0000;
        #1 load <= 1; clear <= 1; clk <= 0; enab <= 1; numero <= 4'b0000;
        #1 load <= 1; clear <= 1; clk <= 1; enab <= 1; numero <= 4'b0000;
        #1 load <= 1; clear <= 1; clk <= 0; enab <= 1; numero <= 4'b0000;
        #1 load <= 1; clear <= 1; clk <= 1; enab <= 1; numero <= 4'b0000;
        #1 load <= 1; clear <= 1; clk <= 0; enab <= 1; numero <= 4'b0000;
        #1 load <= 1; clear <= 1; clk <= 1; enab <= 1; numero <= 4'b0000;
        

        #1 load <= 1; clear <= 0; clk <= 0; enab <= 0; numero <= 4'b0000;
        #1 load <= 1; clear <= 1; clk <= 0; enab <= 0; numero <= 4'b0000;

        // Teste load e tc
        #1 load <= 0; clear <= 1; clk <= 0; enab <= 0; numero <= 4'b0101;
        #1 load <= 1; clear <= 1; clk <= 0; enab <= 1; numero <= 4'b0000;
        #1 load <= 1; clear <= 1; clk <= 1; enab <= 1; numero <= 4'b0000;
        #1 load <= 1; clear <= 1; clk <= 0; enab <= 1; numero <= 4'b0000;
        #1 load <= 1; clear <= 1; clk <= 1; enab <= 1; numero <= 4'b0000;
        #1 load <= 1; clear <= 1; clk <= 0; enab <= 1; numero <= 4'b0000;
        #1 load <= 1; clear <= 1; clk <= 1; enab <= 1; numero <= 4'b0000;
        #1 load <= 1; clear <= 1; clk <= 0; enab <= 1; numero <= 4'b0000;
        #1 load <= 1; clear <= 1; clk <= 1; enab <= 1; numero <= 4'b0000;
        #1 load <= 1; clear <= 1; clk <= 0; enab <= 1; numero <= 4'b0000;
        #1 load <= 1; clear <= 1; clk <= 1; enab <= 1; numero <= 4'b0000;
        #1 load <= 1; clear <= 1; clk <= 0; enab <= 0; numero <= 4'b0000;
        #1 load <= 1; clear <= 1; clk <= 1; enab <= 0; numero <= 4'b0000;
    
        #2;

    end
endmodule

Nivel_1/Nivel_2-MS_Timer/Nivel_3-MS_Timer/TB/Counter_MOD10_TB/Counter_MOD10_TB.vcd
$date
	Fri Apr 14 19:06:56 2023
$end
$version
	Icarus Verilog
$end
$timescale
	1ps
$end
$scope module Counter_MOD10_TB $end
$var wire 1 ! zero_saida $end
$var wire 1 " tc_saida $end
$var wire 4 # numero_saida [3:0] $end
$var reg 1 $ clear $end
$var reg 1 % clk $end
$var reg 1 & enab $end
$var reg 1 ' load $end
$var reg 4 ( numero [3:0] $end
$scope module dut $end
$var wire 1 % clock $end
$var wire 1 $ clrn $end
$var wire 4 ) data [3:0] $end
$var wire 1 & enable $end
$var wire 1 ' loadn $end
$var reg 4 * ones [3:0] $end
$var reg 1 " tc $end
$var reg 1 ! zero $end
$upscope $end
$upscope $end
$enddefinitions $end
$comment Show the parameter values. $end
$dumpall
$end
#0
$dumpvars
b0 *
b0 )
b0 (
1'
0&
0%
1$
b0 #
0"
1!
$end
#1000
1"
1&
#2000
0"
0!
b1001 #
b1001 *
1%
#3000
0%
#4000
b1000 #
b1000 *
1%
#5000
0%
#6000
b111 #
b111 *
1%
#7000
0%
#8000
b110 #
b110 *
1%
#9000
0%
#10000
b101 #
b101 *
1%
#11000
0%
#12000
b100 #
b100 *
1%
#13000
0%
#14000
b11 #
b11 *
1%
#15000
0%
#16000
b10 #
b10 *
1%
#17000
0%
#18000
b1 #
b1 *
1%
#19000
0%
#20000
1"
1!
b0 #
b0 *
1%
#21000
0%
#22000
0"
0!
b1001 #
b1001 *
1%
#23000
1!
b0 #
b0 *
0&
0%
0$
#24000
1$
#25000
0!
b101 #
b101 *
b101 (
b101 )
0'
#26000
b0 (
b0 )
1&
1'
#27000
b100 #
b100 *
1%
#28000
0%
#29000
b11 #
b11 *
1%
#30000
0%
#31000
b10 #
b10 *
1%
#32000
0%
#33000
b1 #
b1 *
1%
#34000
0%
#35000
1"
1!
b0 #
b0 *
1%
#36000
0"
0&
0%
