Nivel_1/Nivel_2-MS_Timer/Nivel_3-MS_Timer/Counter_MOD10.v
module Counter_MOD10 (
    input wire loadn, clrn, clock, enable,
    input wire [3:0] data,
    output reg [3:0] ones, 
    output reg tc, zero
);

    initial 
    begin
        ones <= 0;    
    end

    always @(posedge clock or negedge clrn) 
    begin
        if (!clrn)
            ones <= 4'b0000;
        else
        begin
            if (!loadn)
                ones <= data;
            else
            begin
                if (enable)
                begin
                    if (ones == 4'b0000)
                        ones <= 4'b1001;
                    else
                        ones <= ones - 1;
                end
            end
        end
    end

    always @(ones or enable)
    begin
        if (ones == 0)
            zero <= 1'b1;
        else
            zero <= 1'b0;
        if (ones == 0 && enable)
                tc <= 1'b1;
            else
                tc <= 1'b0;
    end
    
endmodule

Nivel_1/Nivel_2-MS_Timer/Nivel_3-MS_Timer/Counter_MOD6.v
module Counter_MOD6 (
    input wire loadn, clrn, clock, enable,
    input wire [3:0] data,
    output reg [3:0] tens, 
    output reg tc, zero
);

    initial 
    begin
        tens <= 0;    
    end

    always @(posedge clock or negedge clrn or negedge loadn) 
    begin
        if (!clrn)
            tens <= 4'b0000;
        else
        begin
            if (!loadn)
                tens <= data;
            else
            begin
                if (enable)
                begin
                    if (tens == 4'b0000)
                        tens <= 4'b0101;
                    else
                        tens <= tens - 1;
                end
            end
        end
    end

    always @(tens or enable)
    begin
        if (tens == 0)
            zero <= 1'b1;
        else
            zero <= 1'b0;
        if (tens == 0 && enable)
                tc <= 1'b1;
            else
                tc <= 1'b0;
    end
    
endmodule

Nivel_1/Nivel_2-MS_Timer/MS_Timer.v
`include "..\\Nivel_3-MS_Timer\\Counter_MOD10.v"
`include "..\\Nivel_3-MS_Timer\\Counter_MOD6.v"

module MS_Timer(
    input [3:0] data,
    input loadn, clrn, clock, enable,
    output [3:0] sec_ones, sec_tens, mins,
    output reg zero);

    wire tc1, zero1, tc2, zero2, tc3, zero3; 

    Counter_MOD10 C1 (loadn, clrn, clock, enable, data, sec_ones, tc1, zero1);
    Counter_MOD6 C2 (loadn, clrn, clock, tc1, sec_ones, sec_tens, tc2, zero2);
    Counter_MOD10 C3 (loadn, clrn, clock, tc2, sec_tens, mins, tc3, zero3);

    always @(zero1 or zero2 or zero3)
    begin
       zero <= zero1 & zero2 & zero3;
    end

endmodule

Nivel_1/Nivel_2-MS_Timer/TB/MS_Timer_TB.v
`timescale 1ns/1ps
`include "..\\MS_Timer.v"

module MS_Timer_TB ();
    reg [3:0] data;
    reg loadn, clrn, clock, enable;
    wire [3:0] sec_ones, sec_tens, mins;
    wire zero;

    MS_Timer dut (data, loadn, clrn, clock, enable, sec_ones, sec_tens, mins, zero);

    initial
    begin
        $dumpfile("MS_Timer_TB.vcd");
        $dumpvars(0,MS_Timer_TB);

        #0 loadn <= 1; clrn <= 1; clock <= 0; enable <= 0; data <= 4'b0000;
        #1 loadn <= 0; clrn <= 1; clock <= 1; enable <= 0; data <= 4'b0010;
        #1 loadn <= 1; clrn <= 1; clock <= 0; enable <= 0; data <= 4'b0000;
        #1 loadn <= 1; clrn <= 1; clock <= 1; enable <= 0; data <= 4'b0000;
        #1 loadn <= 0; clrn <= 1; clock <= 0; enable <= 0; data <= 4'b0000;
        #1 loadn <= 0; clrn <= 1; clock <= 1; enable <= 0; data <= 4'b1001;
        #1 loadn <= 1; clrn <= 1; clock <= 0; enable <= 0; data <= 4'b0000;
        #1 loadn <= 1; clrn <= 1; clock <= 1; enable <= 0; data <= 4'b0000;
        #1 loadn <= 1; clrn <= 1; clock <= 0; enable <= 1; data <= 4'b0000;
        #1 loadn <= 1; clrn <= 1; clock <= 1; enable <= 1; data <= 4'b0000;
        #1 loadn <= 1; clrn <= 1; clock <= 0; enable <= 1; data <= 4'b0000;
        #1 loadn <= 1; clrn <= 1; clock <= 1; enable <= 1; data <= 4'b0000;
        #1 loadn <= 1; clrn <= 1; clock <= 0; enable <= 1; data <= 4'b0000;
        #1 loadn <= 1; clrn <= 1; clock <= 1; enable <= 1; data <= 4'b0000;
        #1 loadn <= 1; clrn <= 1; clock <= 0; enable <= 1; data <= 4'b0000;
        #1 loadn <= 1; clrn <= 1; clock <= 1; enable <= 1; data <= 4'b0000;
        #1 loadn <= 1; clrn <= 1; clock <= 0; enable <= 0; data <= 4'b0000;
        #1 loadn <= 1; clrn <= 1; clock <= 1; enable <= 0; data <= 4'b0000;
        #1 loadn <= 1; clrn <= 1; clock <= 0; enable <= 0; data <= 4'b0000;
        #1 loadn <= 1; clrn <= 1; clock <= 1; enable <= 0; data <= 4'b0000;
        #1 loadn <= 1; clrn <= 1; clock <= 0; enable <= 1; data <= 4'b0000;
        #1 loadn <= 1; clrn <= 1; clock <= 1; enable <= 1; data <= 4'b0000;
        #1 loadn <= 1; clrn <= 1; clock <= 0; enable <= 1; data <= 4'b0000;
        #1 loadn <= 1; clrn <= 1; clock <= 1; enable <= 1; data <= 4'b0000;
        #1 loadn <= 1; clrn <= 1; clock <= 0; enable <= 1; data <= 4'b0000;
        #1 loadn <= 1; clrn <= 1; clock <= 1; enable <= 1; data <= 4'b0000;
        #1 loadn <= 1; clrn <= 1; clock <= 0; enable <= 1; data <= 4'b0000;
        #1 loadn <= 1; clrn <= 1; clock <= 1; enable <= 1; data <= 4'b0000;
        #1 loadn <= 1; clrn <= 1; clock <= 0; enable <= 1; data <= 4'b0000;
        #1 loadn <= 1; clrn <= 1; clock <= 1; enable <= 1; data <= 4'b0000;
        #1 loadn <= 1; clrn <= 1; clock <= 0; enable <= 1; data <= 4'b0000;
        #1 loadn <= 1; clrn <= 1; clock <= 1; enable <= 1; data <= 4'b0000;
        #1 loadn <= 1; clrn <= 1; clock <= 0; enable <= 1; data <= 4'b0000;
        #1 loadn <= 1; clrn <= 1; clock <= 1; enable <= 1; data <= 4'b0000;
        #1 loadn <= 1; clrn <= 1; clock <= 0; enable <= 1; data <= 4'b0000;
        #1 loadn <= 1; clrn <= 1; clock <= 1; enable <= 1; data <= 4'b0000;
        #1 loadn <= 1; clrn <= 1; clock <= 0; enable <= 1; data <= 4'b0000;
        #1 loadn <= 1; clrn <= 1; clock <= 1; enable <= 1; data <= 4'b0000;
        #1 loadn <= 1; clrn <= 1; clock <= 0; enable <= 1; data <= 4'b0000;
        #1 loadn <= 1; clrn <= 1; clock <= 1; enable <= 1; data <= 4'b0000;
        #1 loadn <= 1; clrn <= 1; clock <= 0; enable <= 1; data <= 4'b0000;
        #1 loadn <= 1; clrn <= 1; clock <= 1; enable <= 1; data <= 4'b0000;
        #1 loadn <= 1; clrn <= 1; clock <= 0; enable <= 1; data <= 4'b0000;
        #1 loadn <= 1; clrn <= 1; clock <= 1; enable <= 1; data <= 4'b0000;
        #1 loadn <= 1; clrn <= 1; clock <= 0; enable <= 1; data <= 4'b0000;
        #1 loadn <= 1; clrn <= 1; clock <= 1; enable <= 1; data <= 4'b0000;
        #1 loadn <= 1; clrn <= 1; clock <= 0; enable <= 1; data <= 4'b0000;
        #1 loadn <= 1; clrn <= 1; clock <= 1; enable <= 1; data <= 4'b0000;
        #1 loadn <= 1; clrn <= 1; clock <= 0; enable <= 1; data <= 4'b0000;
        #1 loadn <= 1; clrn <= 1; clock <= 1; enable <= 1; data <= 4'b0000;
        #1 loadn <= 1; clrn <= 1; clock <= 0; enable <= 1; data <= 4'b0000;
        #1 loadn <= 1; clrn <= 1; clock <= 1; enable <= 1; data <= 4'b0000;
        #1 loadn <= 1; clrn <= 0; clock <= 0; enable <= 1; data <= 4'b0000;
        #1 loadn <= 1; clrn <= 1; clock <= 1; enable <= 1; data <= 4'b0000;
        #1 loadn <= 1; clrn <= 1; clock <= 0; enable <= 1; data <= 4'b0000;
        #1 loadn <= 1; clrn <= 1; clock <= 1; enable <= 1; data <= 4'b0000;
        #1 loadn <= 1; clrn <= 0; clock <= 0; enable <= 0; data <= 4'b0000;
        #1 loadn <= 1; clrn <= 1; clock <= 1; enable <= 0; data <= 4'b0000;

        #2;

        
    end
endmodule

Nivel_1/Nivel_2-MS_Timer/TB/MS_Timer_TB.vcd
$date
	Sat Apr 15 05:43:05 2023
$end
$version
	Icarus Verilog
$end
$timescale
	1ps
$end
$scope module MS_Timer_TB $end
$var wire 1 ! zero $end
$var wire 4 " sec_tens [3:0] $end
$var wire 4 # sec_ones [3:0] $end
$var wire 4 $ mins [3:0] $end
$var reg 1 % clock $end
$var reg 1 & clrn $end
$var reg 4 ' data [3:0] $end
$var reg 1 ( enable $end
$var reg 1 ) loadn $end
$scope module dut $end
$var wire 1 % clock $end
$var wire 1 & clrn $end
$var wire 4 * data [3:0] $end
$var wire 1 ( enable $end
$var wire 1 ) loadn $end
$var wire 1 + zero3 $end
$var wire 1 , zero2 $end
$var wire 1 - zero1 $end
$var wire 1 . tc3 $end
$var wire 1 / tc2 $end
$var wire 1 0 tc1 $end
$var wire 4 1 sec_tens [3:0] $end
$var wire 4 2 sec_ones [3:0] $end
$var wire 4 3 mins [3:0] $end
$var reg 1 ! zero $end
$scope module C1 $end
$var wire 1 % clock $end
$var wire 1 & clrn $end
$var wire 4 4 data [3:0] $end
$var wire 1 ( enable $end
$var wire 1 ) loadn $end
$var reg 4 5 ones [3:0] $end
$var reg 1 0 tc $end
$var reg 1 - zero $end
$upscope $end
$scope module C2 $end
$var wire 1 % clock $end
$var wire 1 & clrn $end
$var wire 4 6 data [3:0] $end
$var wire 1 0 enable $end
$var wire 1 ) loadn $end
$var reg 1 / tc $end
$var reg 4 7 tens [3:0] $end
$var reg 1 , zero $end
$upscope $end
$scope module C3 $end
$var wire 1 % clock $end
$var wire 1 & clrn $end
$var wire 4 8 data [3:0] $end
$var wire 1 / enable $end
$var wire 1 ) loadn $end
$var reg 4 9 ones [3:0] $end
$var reg 1 . tc $end
$var reg 1 + zero $end
$upscope $end
$upscope $end
$upscope $end
$enddefinitions $end
$comment Show the parameter values. $end
$dumpall
$end
#0
$dumpvars
b0 9
b0 8
b0 7
b0 6
b0 5
b0 4
b0 3
b0 2
b0 1
00
0/
0.
1-
1,
1+
b0 *
1)
0(
b0 '
1&
0%
b0 $
b0 #
b0 "
1!
$end
#1000
0!
0-
b10 #
b10 2
b10 5
b10 6
b10 '
b10 *
b10 4
1%
0)
#2000
b0 '
b0 *
b0 4
0%
1)
#3000
1%
#4000
1-
0,
b0 #
b0 2
b0 5
b0 6
b10 "
b10 1
b10 7
b10 8
0%
0)
#5000
0+
1,
0-
b10 $
b10 3
b10 9
b0 "
b0 1
b0 7
b0 8
b1001 #
b1001 2
b1001 5
b1001 6
b1001 '
b1001 *
b1001 4
1%
#6000
b0 '
b0 *
b0 4
0%
1)
#7000
1%
#8000
1(
0%
#9000
b1000 #
b1000 2
b1000 5
b1000 6
1%
#10000
0%
#11000
b111 #
b111 2
b111 5
b111 6
1%
#12000
0%
#13000
b110 #
b110 2
b110 5
b110 6
1%
#14000
0%
#15000
b101 #
b101 2
b101 5
b101 6
1%
#16000
0(
0%
#17000
1%
#18000
0%
#19000
1%
#20000
1(
0%
#21000
b100 #
b100 2
b100 5
b100 6
1%
#22000
0%
#23000
b11 #
b11 2
b11 5
b11 6
1%
#24000
0%
#25000
b10 #
b10 2
b10 5
b10 6
1%
#26000
0%
#27000
b1 #
b1 2
b1 5
b1 6
1%
#28000
0%
#29000
1/
10
1-
b0 #
b0 2
b0 5
b0 6
1%
#30000
0%
#31000
00
0-
0/
0,
b1001 #
b1001 2
b1001 5
b1001 6
b101 "
b101 1
b101 7
b101 8
b1 $
b1 3
b1 9
1%
#32000
0%
#33000
b1000 #
b1000 2
b1000 5
b1000 6
1%
#34000
0%
#35000
b111 #
b111 2
b111 5
b111 6
1%
#36000
0%
#37000
b110 #
b110 2
b110 5
b110 6
1%
#38000
0%
#39000
b101 #
b101 2
b101 5
b101 6
1%
#40000
0%
#41000
b100 #
b100 2
b100 5
b100 6
1%
#42000
0%
#43000
b11 #
b11 2
b11 5
b11 6
1%
#44000
0%
#45000
b10 #
b10 2
b10 5
b10 6
1%
#46000
0%
#47000
b1 #
b1 2
b1 5
b1 6
1%
#48000
0%
#49000
10
1-
b0 #
b0 2
b0 5
b0 6
1%
#50000
0%
#51000
00
0-
b1001 #
b1001 2
b1001 5
b1001 6
b100 "
b100 1
b100 7
b100 8
1%
#52000
1.
1/
1!
1+
1,
10
1-
b0 $
b0 3
b0 9
b0 "
b0 1
b0 7
b0 8
b0 #
b0 2
b0 5
b0 6
0%
0&
#53000
0!
00
0-
0/
0,
0.
0+
b1001 #
b1001 2
b1001 5
b1001 6
b101 "
b101 1
b101 7
b101 8
b1001 $
b1001 3
b1001 9
1%
1&
#54000
0%
#55000
b1000 #
b1000 2
b1000 5
b1000 6
1%
#56000
1!
1-
1,
1+
b0 #
b0 2
b0 5
b0 6
b0 "
b0 1
b0 7
b0 8
b0 $
b0 3
b0 9
0(
0%
0&
#57000
1%
1&
