Nivel_1/Nivel_2-Mag_Control/Nivel_3-Mag_Control/OnOff_Control/OnOff_Control.v
module OnOff_Control (input wire startn, stopn, clearn, door_closed, timer_done,
                       output reg Set, Reset);
    reg start, stop, clear;
    
    always @(startn or stopn or clearn or door_closed or timer_done)
    begin
        start = ~startn;
        stop = ~stopn;
        clear = ~clearn;

        Reset = stop | clear | ~door_closed | timer_done;
        Set = start & door_closed & ~Reset;
    end
endmodule

Nivel_1/Nivel_2-Mag_Control/Nivel_3-Mag_Control/TB/OnOff_Control_TB/OnOff_Control_TB.v
`timescale 1ns/1ps
`include "..\\..\\OnOff_Control.v"

module OnOff_Control_TB ();
    reg Nstart, Nstop, Nclear, door_clo, time_over;
    wire s, r;

    OnOff_Control dut (Nstart, Nstop, Nclear, door_clo, time_over, s, r);

    initial
    begin
        $dumpfile("OnOff_Control_TB.vcd");
        $dumpvars(0,OnOff_Control_TB);

        // Apeta start apenas
        #0 Nstart = 1; Nstop = 1; Nclear = 1; door_clo = 1; time_over = 1;
        #1 Nstart = 0; Nstop = 1; Nclear = 1; door_clo = 1; time_over = 1;
        #1 Nstart = 1; Nstop = 1; Nclear = 1; door_clo = 1; time_over = 1;

        #1 Nstart = 0; Nstop = 0; Nclear = 0; door_clo = 0; time_over = 0;
        #1;

        // Liga até tempo acabar

        #1 Nstart = 1; Nstop = 1; Nclear = 1; door_clo = 1; time_over = 0;
        #1 Nstart = 0; Nstop = 1; Nclear = 1; door_clo = 1; time_over = 0;
        #1 Nstart = 1; Nstop = 1; Nclear = 1; door_clo = 1; time_over = 0;
        #4 Nstart = 1; Nstop = 1; Nclear = 1; door_clo = 1; time_over = 1;
        
        #1 Nstart = 0; Nstop = 0; Nclear = 0; door_clo = 0; time_over = 0;
        #1;

        // Abre a porta no meio
        #1 Nstart = 1; Nstop = 1; Nclear = 1; door_clo = 1; time_over = 0;
        #1 Nstart = 0; Nstop = 1; Nclear = 1; door_clo = 1; time_over = 0;
        #1 Nstart = 1; Nstop = 1; Nclear = 1; door_clo = 1; time_over = 0;
        #2 Nstart = 1; Nstop = 1; Nclear = 1; door_clo = 0; time_over = 0;
        #2 Nstart = 1; Nstop = 1; Nclear = 1; door_clo = 1; time_over = 0;
        #1 Nstart = 0; Nstop = 1; Nclear = 1; door_clo = 1; time_over = 0;
        #1 Nstart = 1; Nstop = 1; Nclear = 1; door_clo = 1; time_over = 0;
        #2 Nstart = 1; Nstop = 1; Nclear = 1; door_clo = 1; time_over = 1;

        #1 Nstart = 0; Nstop = 0; Nclear = 0; door_clo = 0; time_over = 0;
        #1;

        // Para no meio
        #1 Nstart = 1; Nstop = 1; Nclear = 1; door_clo = 1; time_over = 0;
        #1 Nstart = 0; Nstop = 1; Nclear = 1; door_clo = 1; time_over = 0;
        #1 Nstart = 1; Nstop = 1; Nclear = 1; door_clo = 1; time_over = 0;
        #1 Nstart = 1; Nstop = 0; Nclear = 1; door_clo = 1; time_over = 0;
        #1 Nstart = 1; Nstop = 1; Nclear = 1; door_clo = 1; time_over = 0;
        #2 Nstart = 0; Nstop = 1; Nclear = 1; door_clo = 1; time_over = 0;
        #1 Nstart = 1; Nstop = 1; Nclear = 1; door_clo = 1; time_over = 0;
        #2 Nstart = 1; Nstop = 1; Nclear = 1; door_clo = 1; time_over = 1;

        #1;
    end
endmodule

Nivel_1/Nivel_2-Mag_Control/Nivel_3-Mag_Control/TB/OnOff_Control_TB/OnOff_Control_TB.vcd
$date
	Fri Apr 14 10:51:13 2023
$end
$version
	Icarus Verilog
$end
$timescale
	1ps
$end
$scope module OnOff_Control_TB $end
$var wire 1 ! s $end
$var wire 1 " r $end
$var reg 1 # Nclear $end
$var reg 1 $ Nstart $end
$var reg 1 % Nstop $end
$var reg 1 & door_clo $end
$var reg 1 ' time_over $end
$scope module dut $end
$var wire 1 # clearn $end
$var wire 1 & door_closed $end
$var wire 1 $ startn $end
$var wire 1 % stopn $end
$var wire 1 ' timer_done $end
$var reg 1 " Reset $end
$var reg 1 ! Set $end
$var reg 1 ( clear $end
$var reg 1 ) start $end
$var reg 1 * stop $end
$upscope $end
$upscope $end
$enddefinitions $end
$comment Show the parameter values. $end
$dumpall
$end
#0
$dumpvars
0*
0)
0(
1'
1&
1%
1$
1#
1"
0!
$end
#1000
1)
0$
#2000
0)
1$
#3000
1(
1*
1)
0'
0&
0#
0%
0$
#5000
0"
0(
0*
0)
1&
1#
1%
1$
#6000
1!
1)
0$
#7000
0!
0)
1$
#11000
1"
1'
#12000
1(
1*
1)
0'
0&
0#
0%
0$
#14000
0"
0(
0*
0)
1&
1#
1%
1$
#15000
1!
1)
0$
#16000
0!
0)
1$
#18000
1"
0&
#20000
0"
1&
#21000
1!
1)
0$
#22000
0!
0)
1$
#24000
1"
1'
#25000
1(
1*
1)
0'
0&
0#
0%
0$
#27000
0"
0(
0*
0)
1&
1#
1%
1$
#28000
1!
1)
0$
#29000
0!
0)
1$
#30000
1"
1*
0%
#31000
0"
0*
1%
#33000
1!
1)
0$
#34000
0!
0)
1$
#36000
1"
1'
