Nivel_1/Nivel_2-Timer_InControl/Nivel_3-Timer_InControl/Counter_100/Counter_100.v
module Counter_100 (input clock, output reg tic);
    reg [6:0] valor;

    initial 
    begin
        valor <= 0;
    end

    always @(posedge clock) 
    begin
        if (valor == 7'b1100011)
        begin
            valor <= 7'b0000000;
            tic <= 1'b1;
        end
        else
        begin
            valor <= valor + 1;
            tic <= 1'b0;
        end
    end
endmodule

Nivel_1/Nivel_2-Timer_InControl/Nivel_3-Timer_InControl/Counter_100/Counter_100_TB.v
//`timescale 1ns/1ps
`include "Counter_100.v"

module Counter_100_TB ();
    reg clk;
    wire tc;
    reg count;


    Counter_100 dut (clk, tc);

    initial 
    begin
        $dumpfile("Counter_100_TB.vcd");
        $dumpvars(0,Counter_100_TB);

        count = 0;
        while (count < 1)
        begin
            if (clk == 0)
                clk = 1;
            else
                clk = 0;
            
            if (tc == 1)
                count <= count + 1;
            #1;
        end
        clk <= 1;
        #2;
    end
endmodule

Nivel_1/Nivel_2-Timer_InControl/Nivel_3-Timer_InControl/Counter_100/Counter_100_TB.vcd
$date
	Sun Apr 23 02:23:16 2023
$end
$version
	Icarus Verilog
$end
$timescale
	1s
$end
$scope module Counter_100_TB $end
$var wire 1 ! tc $end
$var reg 1 " clk $end
$var reg 1 # count $end
$scope module dut $end
$var wire 1 " clock $end
$var reg 1 ! tic $end
$var reg 7 $ valor [6:0] $end
$upscope $end
$upscope $end
$enddefinitions $end
$comment Show the parameter values. $end
$dumpall
$end
#0
$dumpvars
b0 $
0#
0"
x!
$end
#1
0!
b1 $
1"
#2
0"
#3
b10 $
1"
#4
0"
#5
b11 $
1"
#6
0"
#7
b100 $
1"
#8
0"
#9
b101 $
1"
#10
0"
#11
b110 $
1"
#12
0"
#13
b111 $
1"
#14
0"
#15
b1000 $
1"
#16
0"
#17
b1001 $
1"
#18
0"
#19
b1010 $
1"
#20
0"
#21
b1011 $
1"
#22
0"
#23
b1100 $
1"
#24
0"
#25
b1101 $
1"
#26
0"
#27
b1110 $
1"
#28
0"
#29
b1111 $
1"
#30
0"
#31
b10000 $
1"
#32
0"
#33
b10001 $
1"
#34
0"
#35
b10010 $
1"
#36
0"
#37
b10011 $
1"
#38
0"
#39
b10100 $
1"
#40
0"
#41
b10101 $
1"
#42
0"
#43
b10110 $
1"
#44
0"
#45
b10111 $
1"
#46
0"
#47
b11000 $
1"
#48
0"
#49
b11001 $
1"
#50
0"
#51
b11010 $
1"
#52
0"
#53
b11011 $
1"
#54
0"
#55
b11100 $
1"
#56
0"
#57
b11101 $
1"
#58
0"
#59
b11110 $
1"
#60
0"
#61
b11111 $
1"
#62
0"
#63
b100000 $
1"
#64
0"
#65
b100001 $
1"
#66
0"
#67
b100010 $
1"
#68
0"
#69
b100011 $
1"
#70
0"
#71
b100100 $
1"
#72
0"
#73
b100101 $
1"
#74
0"
#75
b100110 $
1"
#76
0"
#77
b100111 $
1"
#78
0"
#79
b101000 $
1"
#80
0"
#81
b101001 $
1"
#82
0"
#83
b101010 $
1"
#84
0"
#85
b101011 $
1"
#86
0"
#87
b101100 $
1"
#88
0"
#89
b101101 $
1"
#90
0"
#91
b101110 $
1"
#92
0"
#93
b101111 $
1"
#94
0"
#95
b110000 $
1"
#96
0"
#97
b110001 $
1"
#98
0"
#99
b110010 $
1"
#100
0"
#101
b110011 $
1"
#102
0"
#103
b110100 $
1"
#104
0"
#105
b110101 $
1"
#106
0"
#107
b110110 $
1"
#108
0"
#109
b110111 $
1"
#110
0"
#111
b111000 $
1"
#112
0"
#113
b111001 $
1"
#114
0"
#115
b111010 $
1"
#116
0"
#117
b111011 $
1"
#118
0"
#119
b111100 $
1"
#120
0"
#121
b111101 $
1"
#122
0"
#123
b111110 $
1"
#124
0"
#125
b111111 $
1"
#126
0"
#127
b1000000 $
1"
#128
0"
#129
b1000001 $
1"
#130
0"
#131
b1000010 $
1"
#132
0"
#133
b1000011 $
1"
#134
0"
#135
b1000100 $
1"
#136
0"
#137
b1000101 $
1"
#138
0"
#139
b1000110 $
1"
#140
0"
#141
b1000111 $
1"
#142
0"
#143
b1001000 $
1"
#144
0"
#145
b1001001 $
1"
#146
0"
#147
b1001010 $
1"
#148
0"
#149
b1001011 $
1"
#150
0"
#151
b1001100 $
1"
#152
0"
#153
b1001101 $
1"
#154
0"
#155
b1001110 $
1"
#156
0"
#157
b1001111 $
1"
#158
0"
#159
b1010000 $
1"
#160
0"
#161
b1010001 $
1"
#162
0"
#163
b1010010 $
1"
#164
0"
#165
b1010011 $
1"
#166
0"
#167
b1010100 $
1"
#168
0"
#169
b1010101 $
1"
#170
0"
#171
b1010110 $
1"
#172
0"
#173
b1010111 $
1"
#174
0"
#175
b1011000 $
1"
#176
0"
#177
b1011001 $
1"
#178
0"
#179
b1011010 $
1"
#180
0"
#181
b1011011 $
1"
#182
0"
#183
b1011100 $
1"
#184
0"
#185
b1011101 $
1"
#186
0"
#187
b1011110 $
1"
#188
0"
#189
b1011111 $
1"
#190
0"
#191
b1100000 $
1"
#192
0"
#193
b1100001 $
1"
#194
0"
#195
b1100010 $
1"
#196
0"
#197
b1100011 $
1"
#198
0"
#199
1!
b0 $
1"
#200
1#
0"
#201
0!
b1 $
1"
