Nivel_1/Nivel_2-Mag_Control/Nivel_3-Mag_Control/SR_Latch.v
module SR_Latch (input wire S, R, output reg Q);
    reg NQ;

    always @(S or R)
    begin
        NQ = ~(S | Q);
        Q = ~(R | NQ);
        NQ = ~(S | Q);
    end
endmodule

Nivel_1/Nivel_2-Mag_Control/Nivel_3-Mag_Control/SR_Latch/SR_Latch_TB.v
`timescale 1ns/1ps
`include "SR_Latch.v"

module SR_Latch_TB ();
    reg s, r;
    wire q;

    SR_Latch dut (.S(s), .R(r), .Q(q));

    initial
    begin
        $dumpfile("SR_Latch_TB.vcd");
        $dumpvars(0,SR_Latch_TB);

        s <= 0; r <= 0;
        s <=#1 1;
        s <=#3 0;
        r <=#6 1;
        r <=#8 0;
        s <=#9 1;
        s <=#10 0;
        s <=#14 1; r <=#14 1;
        s <=#15 0;
        s <=#16 1;
        r <=#18 0;
        s <=#19 0;
        s <=#20 1; r <=#20 1;
        s <=#22 0; r <=#22 0;
        #24;
    end
endmodule

Nivel_1/Nivel_2-Mag_Control/Nivel_3-Mag_Control/SR_Latch/SR_Latch_TB.vcd
$date
	Sat Apr 22 15:43:24 2023
$end
$version
	Icarus Verilog
$end
$timescale
	1ps
$end
$scope module SR_Latch_TB $end
$var wire 1 ! q $end
$var reg 1 " r $end
$var reg 1 # s $end
$scope module dut $end
$var wire 1 " R $end
$var wire 1 # S $end
$var reg 1 $ NQ $end
$var reg 1 ! Q $end
$upscope $end
$upscope $end
$enddefinitions $end
$comment Show the parameter values. $end
$dumpall
$end
#0
$dumpvars
x$
0#
0"
x!
$end
#1000
1!
0$
1#
#3000
0#
#6000
1$
0!
1"
#8000
0"
#9000
1!
0$
1#
#10000
0#
#14000
0!
1"
1#
#15000
1$
0#
#16000
0$
1#
#18000
1!
0"
#19000
0#
#20000
0!
1"
1#
#22000
1$
0"
0#
